[
  {
    "enabled": true,
    "map_file_name": "D2083",
    "monster_name": "Evil Mir",
    "body_name": "00",
    "location": {
      "x": 82,
      "y": 44
    },
    "drop_area_top": {
      "x": 75,
      "y": 45
    },
    "drop_area_bottom": {
      "x": 86,
      "y": 57
    },
    "level": 1,
    "experience": 0,
    "exps": [
      10000,
      20000,
      30000,
      40000,
      50000,
      60000,
      70000,
      80000,
      90000,
      100000,
      110000,
      120000
    ],
    "drops": [
      [],
      [],
      [],
      [],
      [],
      [],
      [],
      [],
      [],
      [],
      [],
      [],
      []
    ]
  }
]